safeguards/__init__.py
safeguards/exceptions.py
safeguards/types.py
safeguards/api/__init__.py
safeguards/api/base.py
safeguards/api/budget_override_routes.py
safeguards/api/factory.py
safeguards/api/slack_interaction.py
safeguards/api/v1.py
safeguards/base/__init__.py
safeguards/base/auth.py
safeguards/base/budget.py
safeguards/base/budget_coordinator.py
safeguards/base/budget_impl.py
safeguards/base/guardrails.py
safeguards/base/monitoring.py
safeguards/base/security.py
safeguards/budget/__init__.py
safeguards/budget/api_tracker.py
safeguards/budget/cost_estimation.py
safeguards/budget/cost_tracker.py
safeguards/budget/dashboard_server.py
safeguards/budget/manager.py
safeguards/budget/realtime_tracker.py
safeguards/budget/simple_budget.py
safeguards/budget/token_tracker.py
safeguards/budget/templates/dashboard.html
safeguards/config/__init__.py
safeguards/config/config.py
safeguards/core/__init__.py
safeguards/core/alert_types.py
safeguards/core/budget_coordination.py
safeguards/core/budget_override.py
safeguards/core/budget_reservation.py
safeguards/core/cache_manager.py
safeguards/core/cost_management.py
safeguards/core/dynamic_budget.py
safeguards/core/memory_manager.py
safeguards/core/monitoring.py
safeguards/core/notification_manager.py
safeguards/core/notifications.py
safeguards/core/pool_health.py
safeguards/core/resilience.py
safeguards/core/safety_controller.py
safeguards/core/transaction.py
safeguards/guardrails/__init__.py
safeguards/guardrails/budget.py
safeguards/guardrails/resource.py
safeguards/human_action/__init__.py
safeguards/monitoring/__init__.py
safeguards/monitoring/budget_monitor.py
safeguards/monitoring/metrics.py
safeguards/monitoring/metrics_analyzer.py
safeguards/monitoring/resource_monitor.py
safeguards/monitoring/storage.py
safeguards/monitoring/system_monitor.py
safeguards/monitoring/violation_reporter.py
safeguards/notifications/__init__.py
safeguards/notifications/channels.py
safeguards/notifications/manager.py
agent_safeguards-0.1.3.dist-info/METADATA
agent_safeguards-0.1.3.dist-info/WHEEL
agent_safeguards-0.1.3.dist-info/licenses/LICENSE
agent_safeguards-0.1.3.dist-info/RECORD
