Metadata-Version: 2.4
Name: agent-safeguards
Version: 0.1.3
Summary: Safeguards for custom agents.
Project-URL: Homepage, https://github.com/cirbuk/agent-safeguards
Project-URL: Documentation, https://github.com/cirbuk/agent-safeguards/tree/main/docs
Project-URL: Issues, https://github.com/cirbuk/agent-safeguards/issues
Project-URL: Changelog, https://github.com/cirbuk/agent-safeguards/blob/main/CHANGELOG.md
Author-email: "Dev Team @mason" <dev@getmason.io>
License: MIT License
License-File: LICENSE
Classifier: Development Status :: 3 - Alpha
Classifier: Intended Audience :: Developers
Classifier: License :: OSI Approved :: MIT License
Classifier: Operating System :: OS Independent
Classifier: Programming Language :: Python :: 3 :: Only
Classifier: Programming Language :: Python :: 3.10
Classifier: Programming Language :: Python :: 3.11
Classifier: Topic :: Scientific/Engineering :: Artificial Intelligence
Requires-Python: >=3.10
Requires-Dist: aiohttp>=3.8.0
Requires-Dist: asyncio>=3.4.3
Requires-Dist: fastapi>=0.109.0
Requires-Dist: jinja2>=3.1.0
Requires-Dist: numpy>=1.24.0
Requires-Dist: pandas>=2.0.0
Requires-Dist: plotly>=5.13.0
Requires-Dist: prometheus-client>=0.17.0
Requires-Dist: psutil>=5.9.0
Requires-Dist: pydantic>=2.0.0
Requires-Dist: python-dateutil>=2.8.0
Requires-Dist: python-dotenv>=1.0.0
Requires-Dist: pyyaml>=6.0.0
Requires-Dist: requests>=2.30.0
Requires-Dist: ruff>=0.11.6
Requires-Dist: scikit-learn>=1.3.0
Requires-Dist: scipy>=1.10.0
Requires-Dist: tenacity>=8.2.0
Requires-Dist: typing-extensions>=4.0.0
Requires-Dist: uvicorn>=0.27.0
Requires-Dist: websockets>=10.4
Provides-Extra: dev
Requires-Dist: bandit>=1.7.0; extra == 'dev'
Requires-Dist: black>=23.0.0; extra == 'dev'
Requires-Dist: isort>=5.12.0; extra == 'dev'
Requires-Dist: mypy>=1.7.0; extra == 'dev'
Requires-Dist: pre-commit>=2.15.0; extra == 'dev'
Requires-Dist: pylint>=3.0.0; extra == 'dev'
Requires-Dist: setuptools>=65.5.1; extra == 'dev'
Requires-Dist: types-psutil>=5.9.0; extra == 'dev'
Requires-Dist: types-requests>=2.30.0; extra == 'dev'
Provides-Extra: docs
Requires-Dist: sphinx-autodoc-typehints>=1.23.0; extra == 'docs'
Requires-Dist: sphinx-rtd-theme>=1.2.0; extra == 'docs'
Requires-Dist: sphinx>=6.0.0; extra == 'docs'
Provides-Extra: test
Requires-Dist: pytest-asyncio>=0.23.0; extra == 'test'
Requires-Dist: pytest-cov>=4.1.0; extra == 'test'
Requires-Dist: pytest>=7.0.0; extra == 'test'
